setup.py
mirai/__init__.py
mirai/_version.py
mirai/exceptions.py
mirai/futures.py
mirai/pool.py
mirai/utils.py
mirai.egg-info/PKG-INFO
mirai.egg-info/SOURCES.txt
mirai.egg-info/dependency_links.txt
mirai.egg-info/requires.txt
mirai.egg-info/top_level.txt
mirai/tests/__init__.py
mirai/tests/test_futures.py
mirai/tests/test_pool.py