Metadata-Version: 1.1
Name: mirai
Version: 0.1.5
Summary: Twitter Futures in Python
Home-page: http://github.com/duckworthd/mirai
Author: Daniel Duckworth
Author-email: duckworthd@gmail.com
License: BSD
Keywords: futures concurrent finagle twitter
Platform: UNKNOWN
Classifier: Development Status :: 4 - Beta
Classifier: License :: OSI Approved :: BSD License
Classifier: Operating System :: OS Independent
Classifier: Programming Language :: Python
